datakit_github/__init__.py
datakit_github/github_api.py
datakit_github/project_mixin.py
datakit_github/repository.py
datakit_github/commands/__init__.py
datakit_github/commands/integrate.py
tests/__init__.py
tests/conftest.py
tests/test_github_api.py
tests/test_repository.py
tests/cassettes/test_accounts.yaml
tests/commands/__init__.py
tests/commands/test_integrate.py
tests/commands/test_integrate_basic.py
tests/commands/cassettes/test_choose_default_account.yaml
tests/commands/cassettes/test_choose_default_account_basic.yaml
tests/commands/cassettes/test_choose_org_account_private_error.yaml
tests/commands/cassettes/test_choose_org_account_public_repo.yaml
tests/commands/cassettes/test_repo_already_exists.yaml
tests/commands/cassettes/test_repo_already_exists_org_account.yaml
tests/commands/cassettes/test_repo_already_initialized.yaml
tests/commands/cassettes/test_return_chosen_inputs.yaml
datakit_github-0.2.1.dist-info/AUTHORS.rst
datakit_github-0.2.1.dist-info/LICENSE
datakit_github-0.2.1.dist-info/METADATA
datakit_github-0.2.1.dist-info/WHEEL
datakit_github-0.2.1.dist-info/entry_points.txt
datakit_github-0.2.1.dist-info/top_level.txt
datakit_github-0.2.1.dist-info/RECORD
