Metadata-Version: 2.1
Name: datakit-github
Version: 0.2.1
Summary: Light-weight GitHub integration for datakit workflows.
Home-page: https://github.com/associatedpress/datakit-github
Author: Serdar Tumgoren
Author-email: zstumgoren@gmail.com
License: ISC license
Project-URL: Documentation, http://datakit-github.readthedocs.io/en/latest/
Project-URL: Maintainer, https://github.com/associatedpress
Project-URL: Source, https://github.com/associatedpress/datakit-github
Project-URL: Tracker, https://github.com/associatedpress/datakit-github/issues
Keywords: datakit
Platform: UNKNOWN
Classifier: Development Status :: 5 - Production/Stable
Classifier: Environment :: Console
Classifier: Intended Audience :: Developers
Classifier: License :: OSI Approved :: ISC License (ISCL)
Classifier: Natural Language :: English
Classifier: Programming Language :: Python :: 3
Classifier: Programming Language :: Python :: 3.5
Classifier: Programming Language :: Python :: 3.6
Classifier: Programming Language :: Python :: 3.7
Classifier: Programming Language :: Python :: 3.8
Classifier: Programming Language :: Python :: 3.9
Requires-Dist: cliff
Requires-Dist: datakit-core
Requires-Dist: PyGithub
